nem12_tools/__init__.py
nem12_tools/__main__.py
nem12_tools/cli.py
nem12_tools/py.typed
nem12_tools/generators/__init__.py
nem12_tools/generators/nem12.py
nem12_tools/generators/notifications.py
nem12_tools/parsers/__init__.py
nem12_tools/parsers/nmid.py
nem12_tools-0.1.1.dist-info/METADATA
nem12_tools-0.1.1.dist-info/WHEEL
nem12_tools-0.1.1.dist-info/entry_points.txt
nem12_tools-0.1.1.dist-info/licenses/LICENSE
nem12_tools-0.1.1.dist-info/RECORD
