Metadata-Version: 2.3
Name: nem12_tools
Version: 0.1.1
Summary: Generate NEM12 files for testing
Project-URL: repository, https://github.com/jarshwah/nem12-generator
Project-URL: documentation, https://github.com/jarshwah/nem12-generator
Project-URL: issues, https://github.com/jarshwah/nem12-generator/issues
Author-email: Josh Smeaton <josh.smeaton@gmail.com>
Maintainer-email: Josh Smeaton <josh.smeaton@gmail.com>
License: MIT License
License-File: LICENSE
Classifier: Development Status :: 3 - Alpha
Classifier: License :: OSI Approved :: MIT License
Classifier: Programming Language :: Python :: 3.11
Classifier: Programming Language :: Python :: 3.12
Classifier: Programming Language :: Python :: 3.13
Classifier: Typing :: Typed
Requires-Python: >=3.11
Requires-Dist: click>=8.1.2
Requires-Dist: lxml>=5.0.0
Requires-Dist: pydantic>=2.5.0
